Metadata-Version: 1.1
Name: send-ses-message
Version: 0.1.2
Summary: Send email using the Amazon SES IMAP interface
Home-page: https://github.com/ejstronge/send_ses_message/
Author: Edward J. Stronge
Author-email: ejstronge@gmail.com
License: MIT
Download-URL: https://github.com/ejstronge/send_ses_message/tarball/0.1.1
Keywords: aws ses email
Platform: UNKNOWN
